cat/__init__.py
cat/cli.py
cat/constants.py
cat/dataset.py
cat/report.py
cat/utils.py
cat_python-1.1.0.dist-info/METADATA
cat_python-1.1.0.dist-info/WHEEL
cat_python-1.1.0.dist-info/entry_points.txt
cat_python-1.1.0.dist-info/licenses/LICENSE
cat_python-1.1.0.dist-info/RECORD
