Metadata-Version: 2.3
Name: cat-python
Version: 1.1.0
Summary: Cluster Alignment Tool (CAT)
Project-URL: Documentation, https://brickmanlabcat.readthedocs.io/
Project-URL: Source, https://github.com/brickmanlab/cat-python
Project-URL: Homepage, https://github.com/brickmanlab/cat-python
Author-email: Alex Valentin Nielsen <alexander.nielsen@nbi.ku.dk>, Martin Proks <martin.proks@sund.ku.dk>, Ala Trusina <trusina@nbi.ku.dk>
Maintainer-email: Martin Proks <martin.proks@sund.ku.dk>
License: MIT License
License-File: LICENSE
Classifier: Development Status :: 4 - Beta
Classifier: Intended Audience :: Science/Research
Classifier: License :: OSI Approved :: MIT License
Classifier: Programming Language :: Python :: 3.10
Classifier: Topic :: Scientific/Engineering :: Artificial Intelligence
Classifier: Topic :: Scientific/Engineering :: Bio-Informatics
Requires-Python: >=3.10
Requires-Dist: anndata
Requires-Dist: plotly
Requires-Dist: polars
Requires-Dist: pyarrow
Requires-Dist: rich
Requires-Dist: rich-argparse
Requires-Dist: xlsxwriter
Provides-Extra: dev
Requires-Dist: pre-commit; extra == 'dev'
Provides-Extra: doc
Requires-Dist: myst-nb>=1.1; extra == 'doc'
Requires-Dist: setuptools; extra == 'doc'
Requires-Dist: sphinx-book-theme>=1; extra == 'doc'
Requires-Dist: sphinx>=4.0; extra == 'doc'
Requires-Dist: sphinxcontrib-bibtex>=1; extra == 'doc'
